pysparks-0.1.1.dist-info/licenses/LICENSE
sparks/__init__.py
sparks/core.py
sparks/data/__init__.py
sparks/data/initiators.py
sparks/data/monomers.py
sparks/models/__init__.py
sparks/models/model.py
sparks/models/reactions.py
sparks/models/state.py
sparks/models/FRP2_DAE/__init__.py
sparks/models/FRP2_DAE/equations.py
sparks/models/FRP2_DAE/model.py
sparks/models/FRP2_DAE/reactions.py
sparks/models/FRP2_DAE/ex/CRP2.py
sparks/models/FRP2_DAE/ex/FRP2.py
sparks/models/FRP2_DAE/ex/__init__.py
sparks/models/FRP2_ODE/__init__.py
sparks/models/FRP2_ODE/equations.py
sparks/models/FRP2_ODE/kmc.py
sparks/models/FRP2_ODE/model.py
sparks/models/FRP2_ODE/reactions.py
sparks/models/FRP2_ODE/ex/CRP2.py
sparks/models/FRP2_ODE/ex/FRP2.py
sparks/models/FRP2_ODE/ex/__init__.py
sparks/models/FRP2_ODE_Full/__init__.py
sparks/models/FRP2_ODE_Full/equations.py
sparks/models/FRP2_ODE_Full/model.py
sparks/models/FRP2_ODE_Full/ex/AMS_MMA.py
sparks/models/FRP2_ODE_Full/ex/__init__.py
sparks/simulators/__init__.py
sparks/simulators/base.py
sparks/simulators/deterministic/__init__.py
sparks/simulators/deterministic/base.py
sparks/simulators/deterministic/compile.py
sparks/simulators/deterministic/reactions.py
sparks/simulators/stochastic/__init__.py
sparks/simulators/stochastic/base.py
sparks/utils/__init__.py
sparks/utils/formulas.py
sparks/utils/print.py
pysparks-0.1.1.dist-info/METADATA
pysparks-0.1.1.dist-info/WHEEL
pysparks-0.1.1.dist-info/top_level.txt
pysparks-0.1.1.dist-info/RECORD
