Metadata-Version: 2.4
Name: pysparks
Version: 0.1.1
Summary: Software for Polymerization and Reaction Kinetics Simulations
Author-email: Devon Callan <devoncallan@ucsb.edu>
License: MIT
Project-URL: Homepage, https://github.com/devoncallan/SPaRKS
Project-URL: Repository, https://github.com/devoncallan/SPaRKS
Requires-Python: >=3.10
License-File: LICENSE
Requires-Dist: numpy
Requires-Dist: pandas
Requires-Dist: scipy
Requires-Dist: matplotlib
Requires-Dist: tqdm
Requires-Dist: pyyaml
Requires-Dist: runkmc==0.1.1
Requires-Dist: jupyter
Requires-Dist: notebook
Requires-Dist: ipykernel
Dynamic: license-file
